finnish_media_scrapers/__init__.py
finnish_media_scrapers/fetch.py
finnish_media_scrapers/htmltotext.py
finnish_media_scrapers/query.py
finnish_media_scrapers/scripts/__init__.py
finnish_media_scrapers/scripts/fetch_hs.py
finnish_media_scrapers/scripts/fetch_open.py
finnish_media_scrapers/scripts/htmltotext_hs.py
finnish_media_scrapers/scripts/htmltotext_il.py
finnish_media_scrapers/scripts/htmltotext_is.py
finnish_media_scrapers/scripts/htmltotext_svyle.py
finnish_media_scrapers/scripts/htmltotext_yle.py
finnish_media_scrapers/scripts/post_filter.py
finnish_media_scrapers/scripts/query_hs.py
finnish_media_scrapers/scripts/query_il.py
finnish_media_scrapers/scripts/query_is.py
finnish_media_scrapers/scripts/query_yle.py
finnish_media_scrapers-1.1.4.dist-info/entry_points.txt
finnish_media_scrapers-1.1.4.dist-info/LICENSE
finnish_media_scrapers-1.1.4.dist-info/WHEEL
finnish_media_scrapers-1.1.4.dist-info/METADATA
finnish_media_scrapers-1.1.4.dist-info/RECORD
