Metadata-Version: 2.1
Name: finnish-media-scrapers
Version: 1.1.4
Summary: Scrapers for extracting articles from Finnish journalistic media websites.
Home-page: https://github.com/hsci-r/finnish-media-scraper/
License: MIT
Keywords: Web scraping,Media research
Author: Human Sciences - Computing Interaction Research Group
Author-email: eetu.makela@helsinki.fi
Requires-Python: >=3.7.1,<4.0
Classifier: Environment :: Console
Classifier: Intended Audience :: Science/Research
Classifier: License :: OSI Approved :: MIT License
Classifier: Operating System :: OS Independent
Classifier: Programming Language :: Python :: 3
Classifier: Programming Language :: Python :: 3.10
Classifier: Programming Language :: Python :: 3.8
Classifier: Programming Language :: Python :: 3.9
Classifier: Topic :: Internet :: WWW/HTTP :: Dynamic Content :: News/Diary
Classifier: Topic :: Text Processing :: Markup :: HTML
Provides-Extra: docs
Requires-Dist: Sphinx (>=4.0.2,<5.0.0); extra == "docs"
Requires-Dist: aiohttp (>=3.7.4,<4.0.0)
Requires-Dist: attrs (>=21.2.0,<22.0.0)
Requires-Dist: beautifulsoup4 (>=4.9.3,<5.0.0)
Requires-Dist: lxml (>=4.6.3,<5.0.0)
Requires-Dist: pyppeteer (>=0.2.5,<0.3.0)
Requires-Dist: sphinx-rtd-theme (>=0.5.2,<0.6.0); extra == "docs"
Project-URL: Documentation, https://finnish-media-scrapers.readthedocs.io/
Project-URL: Repository, https://github.com/hsci-r/finnish-media-scraper/
